<?xml version="1.0" encoding="UTF-8"?>
<!DOCTYPE mapper PUBLIC "-//mybatis.org//DTD Mapper 3.0//EN"
  "http://mybatis.org/dtd/mybatis-3-mapper.dtd">
<mapper namespace="dao.MainDAO">

    <select id="getBannerPicByBannerId" resultType="String">
        SELECT bannerPic
        FROM banner
        WHERE bannerId = #{bannerId}
    </select>

	<select id="getMemberCount" resultType="int">
		SELECT COUNT(*) FROM member
		</select>
	<select id="getEnterCount" resultType="int">
		SELECT COUNT(*) FROM enterprise
		</select>
	<select id="getBoardCount" resultType="int">
		SELECT COUNT(*) FROM board
		</select>
</mapper>